[{"date": "20240302", "type": "road", "name": "Vinterkarusellen 6. løp - Mandal", "distance": "3 km, 10 km", "distance_m": [3000, 10000], "place": "Mandal, NOR", "organizer": "Kristiansand Løpeklubb", "website": "", "website_ai_fallback": "Vinterkarusellen 6. løp - Mandal", "src_url": "https://live.eqtiming.com", "created_date": "2024-02-27 13:44:47", "updated_date": "2024-02-27 13:44:47", "id": "vinterkarusellen-6-løp-mandal_20240302_httpsliveeqtimingcom", "extract_id": "7aa7ed33-ebca-4d81-aeb9-4637f62644c9"}, {"date": "20240302", "type": "road", "name": "Egersund Halvmaraton / Mila", "distance": "Halvmaraton, 10 KM", "distance_m": [21097, 10000], "place": "Espelandshallen,Eigersund, NOR", "organizer": "Egersunds Idrettsklubb", "website": "", "website_ai_fallback": "Egersund Halvmaraton / Mila", "src_url": "https://live.eqtiming.com", "created_date": "2024-02-27 13:44:49", "updated_date": "2024-02-27 13:44:49", "id": "egersund-halvmaraton-mila_20240302_httpsliveeqtimingcom", "extract_id": "22b7c014-2bf0-44d8-862b-5720c7487f58"}, {"date": "20240303", "type": "road", "name": "Lierløpet 2", "distance": "Omgang 1", "distance_m": [], "place": "Lier, NOR", "organizer": "Nærsnes Løpeklubb", "website": "", "website_ai_fallback": "Lierløpet 2", "src_url": "https://live.eqtiming.com", "created_date": "2024-02-27 13:44:50", "updated_date": "2024-02-27 13:44:50", "id": "lierløpet-2_20240303_httpsliveeqtimingcom", "extract_id": "a7bd3df4-3c22-4a6d-914a-77f9cff67f56"}, {"date": "20240309", "type": "road", "name": "Orremilå 2024", "distance": "10 km, 5 km", "distance_m": [10000, 5000], "place": "Klepp, NOR", "organizer": "Undheim IL", "website": "http://www.orreil.no/", "website_ai_fallback": "Orremilå 2024", "src_url": "https://live.eqtiming.com", "created_date": "2024-02-27 13:44:52", "updated_date": "2024-02-27 13:44:52", "id": "orremilå-2024_20240309_httpsliveeqtimingcom", "extract_id": "1f433b26-c08f-4a61-925a-8338b282763d"}, {"date": "20240316", "type": "road", "name": "Kondiskarusellen 4. løp", "distance": "5 km, 10 km", "distance_m": [5000, 10000], "place": "Kristiansand, NOR", "organizer": "Kristiansand Løpeklubb", "website": "", "website_ai_fallback": "Kondiskarusellen 4. løp", "src_url": "https://live.eqtiming.com", "created_date": "2024-02-27 13:44:53", "updated_date": "2024-02-27 13:44:53", "id": "kondiskarusellen-4-løp_20240316_httpsliveeqtimingcom", "extract_id": "8e3efcdf-3bf8-482f-8c93-ccad449d2763"}, {"date": "20240316", "type": "road", "name": "Industriløpet 2024", "distance": "5 km, 10 km", "distance_m": [5000, 10000], "place": "Eldøyane, Stord, NOR", "organizer": "Stord IL", "website": "", "website_ai_fallback": "Industriløpet 2024", "src_url": "https://live.eqtiming.com", "created_date": "2024-02-27 13:44:55", "updated_date": "2024-02-27 13:44:55", "id": "industriløpet-2024_20240316_httpsliveeqtimingcom", "extract_id": "b25a2ee7-7127-4c48-abba-394789ce6663"}, {"date": "20240321", "type": "road", "name": "Tjømejoggen", "distance": "10 km, 5 km, 2 km", "distance_m": [10000, 5000, 2000], "place": "Tjøme, NOR", "organizer": "Tjøme Løpeklubb", "website": "", "website_ai_fallback": "Tjømejoggen", "src_url": "https://live.eqtiming.com", "created_date": "2024-02-27 13:44:57", "updated_date": "2024-02-27 13:44:57", "id": "tjømejoggen_20240321_httpsliveeqtimingcom", "extract_id": "314c98af-e897-4086-b65e-19f06260b6db"}, {"date": "20240324", "type": "road", "name": "Lierløpet 3", "distance": "Omgang 1", "distance_m": [], "place": "Lier, NOR", "organizer": "Nærsnes Løpeklubb", "website": "", "website_ai_fallback": "Lierløpet 3", "src_url": "https://live.eqtiming.com", "created_date": "2024-02-27 13:44:58", "updated_date": "2024-02-27 13:44:58", "id": "lierløpet-3_20240324_httpsliveeqtimingcom", "extract_id": "097c65ee-e1ad-4841-9ec4-2daa4a02876d"}, {"date": "20240407", "type": "road", "name": "H3 Hamar HOKA Vårløp 2024", "distance": "H3 Hamar HOKA Våløp, H3 Hamar Hoka Vårløp", "distance_m": [], "place": "Hamar, NOR", "organizer": "Hamar IL", "website": "https://www.h3hamar.no/varlop/", "website_ai_fallback": "H3 Hamar HOKA Vårløp 2024", "src_url": "https://live.eqtiming.com", "created_date": "2024-02-27 13:45:00", "updated_date": "2024-02-27 13:45:00", "id": "h3-hamar-hoka-vårløp-2024_20240407_httpsliveeqtimingcom", "extract_id": "a2df8297-720f-4f7d-abfa-e98808e1edff"}, {"date": "20240407", "type": "road", "name": "Drammen10K 2024", "distance": "Omgang 1", "distance_m": [], "place": "Drammen, NOR", "organizer": "Sturla IF", "website": "", "website_ai_fallback": "Drammen10K 2024", "src_url": "https://live.eqtiming.com", "created_date": "2024-02-27 13:45:01", "updated_date": "2024-02-27 13:45:01", "id": "drammen10k-2024_20240407_httpsliveeqtimingcom", "extract_id": "8a2a745d-c5a9-43fb-be50-64a8a0012f80"}, {"date": "20240409", "type": "road", "name": "Kondiskarusellen 5. løp", "distance": "5 km, 10 km", "distance_m": [5000, 10000], "place": "Kristiansand, NOR", "organizer": "Kristiansand Løpeklubb", "website": "", "website_ai_fallback": "Kondiskarusellen 5. løp", "src_url": "https://live.eqtiming.com", "created_date": "2024-02-27 13:45:02", "updated_date": "2024-02-27 13:45:02", "id": "kondiskarusellen-5-løp_20240409_httpsliveeqtimingcom", "extract_id": "97068a4b-2d89-42e6-b8ce-b917571821ec"}, {"date": "20240414", "type": "road", "name": "Norgestesten løp 1", "distance": "5 km, 10 km, Halvmaraton", "distance_m": [5000, 10000, 21097], "place": "Jessheim, NOR", "organizer": "Ullensaker/Kisa IL", "website": "https://norgestesten.no/", "website_ai_fallback": "Norgestesten løp 1", "src_url": "https://live.eqtiming.com", "created_date": "2024-02-27 13:45:04", "updated_date": "2024-02-27 13:45:04", "id": "norgestesten-løp-1_20240414_httpsliveeqtimingcom", "extract_id": "28cc78b0-c669-4ebd-a87b-da6688c3bcc1"}, {"date": "20240420", "type": "road", "name": "Nordlo Sentrumsløpet", "distance": "Sentrumsløpet Haugesund, Barneløp", "distance_m": [], "place": "Haugesund, NOR", "organizer": "Haugesund Triatlonklubb", "website": "http://sentrumslopethaugesund.no/", "website_ai_fallback": "Nordlo Sentrumsløpet", "src_url": "https://live.eqtiming.com", "created_date": "2024-02-27 13:45:05", "updated_date": "2024-02-27 13:45:05", "id": "nordlo-sentrumsløpet_20240420_httpsliveeqtimingcom", "extract_id": "6abb7c75-f339-4cd8-abe2-53e5a7f68f02"}, {"date": "20240421", "type": "road", "name": "Ørasprinten 2024", "distance": "5 km", "distance_m": [5000], "place": "Kulørn - Kyrksæterøra, NOR", "organizer": "Kyrksæterøra IL", "website": "", "website_ai_fallback": "Ørasprinten 2024", "src_url": "https://live.eqtiming.com", "created_date": "2024-02-27 13:45:08", "updated_date": "2024-02-27 13:45:08", "id": "ørasprinten-2024_20240421_httpsliveeqtimingcom", "extract_id": "074fab7b-2037-4f27-aed8-8488436a4013"}, {"date": "20240421", "type": "road", "name": "Halden Byløp 2024", "distance": "1500m Intersport, 5K NIVÅ, 10K NIVÅ", "distance_m": [5000, 10000], "place": "Halden, NOR", "organizer": "Halden IL", "website": "http://halden-il.idrettenonline.no/", "website_ai_fallback": "Halden Byløp 2024", "src_url": "https://live.eqtiming.com", "created_date": "2024-02-27 13:45:09", "updated_date": "2024-02-27 13:45:09", "id": "halden-byløp-2024_20240421_httpsliveeqtimingcom", "extract_id": "bf6394e4-405a-46ae-90f9-9a35523d5975"}, {"date": "20240421", "type": "road", "name": "Romsdal 5/10/halv", "distance": "5 km, 10 km, Halvmaraton", "distance_m": [5000, 10000, 21097], "place": "Hustadvika, NOR", "organizer": "Molde og Omegn IF", "website": "https://www.romsdal510halv.no/", "website_ai_fallback": "Romsdal 5/10/halv", "src_url": "https://live.eqtiming.com", "created_date": "2024-02-27 13:45:12", "updated_date": "2024-02-27 13:45:12", "id": "romsdal-510halv_20240421_httpsliveeqtimingcom", "extract_id": "fe760093-a50e-43fc-adc4-c8e801083923"}, {"date": "20240421", "type": "road", "name": "Perseløpet  5km,10km, halvmaraton, maraton og 50km_vår", "distance": "Maraton, 50km, Halvmaraton", "distance_m": [42195, 21097], "place": "Ås skole, Hammerås, Eidsvoll, NOR", "organizer": "Feiring IL", "website": "http://www.xn--perselpet-q8a.com/", "website_ai_fallback": "Perseløpet  5km,10km, halvmaraton, maraton og 50km_vår", "src_url": "https://live.eqtiming.com", "created_date": "2024-02-27 13:45:14", "updated_date": "2024-02-27 13:45:14", "id": "perseløpet-5km10km-halvmaraton-maraton-og-50km_vår_20240421_httpsliveeqtimingcom", "extract_id": "535c3f6a-b051-4bb2-b358-0a56c0f53ad3"}, {"date": "20240423", "type": "road", "name": "Trønderjogg 2024", "distance": "5 km gange, 5 km, 10 km", "distance_m": [5000, 5000, 10000], "place": "Trondheim Stadion, NOR", "organizer": "Strindheim IL", "website": "", "website_ai_fallback": "Trønderjogg 2024", "src_url": "https://live.eqtiming.com", "created_date": "2024-02-27 13:45:15", "updated_date": "2024-02-27 13:45:15", "id": "trønderjogg-2024_20240423_httpsliveeqtimingcom", "extract_id": "59ec286a-158f-47ac-8619-01525f88bd45"}, {"date": "20240427", "type": "road", "name": "Fevik halvmaraton & 5km", "distance": "5 km, Halvmaraton", "distance_m": [5000, 21097], "place": "Fevik, NOR", "organizer": "Idrettslaget Express", "website": "", "website_ai_fallback": "Fevik halvmaraton & 5km", "src_url": "https://live.eqtiming.com", "created_date": "2024-02-27 13:45:17", "updated_date": "2024-02-27 13:45:17", "id": "fevik-halvmaraton-5km_20240427_httpsliveeqtimingcom", "extract_id": "1af6de90-5cfd-4de9-8dae-0d714fb13ac1"}, {"date": "20240427", "type": "road", "name": "Fjordkraft Bergen City Marathon 2024", "distance": "Omgang 1", "distance_m": [], "place": "Bergen, NOR", "organizer": "Viking, TIF", "website": "https://www.bergencitymarathon.no/", "website_ai_fallback": "Fjordkraft Bergen City Marathon 2024", "src_url": "https://live.eqtiming.com", "created_date": "2024-02-27 13:45:18", "updated_date": "2024-02-27 13:45:18", "id": "fjordkraft-bergen-city-marathon-2024_20240427_httpsliveeqtimingcom", "extract_id": "afb2e51c-5a96-42e5-a75e-eb8dced3f569"}, {"date": "20240427", "type": "road", "name": "ASICS Sentrumsløpet 2024", "distance": "10 Kilotmeter, 5 Kilometer", "distance_m": [], "place": "OSLO, NOR", "organizer": "Idrottslaget i BUL", "website": "https://sentrumslopet.no/", "website_ai_fallback": "ASICS Sentrumsløpet 2024", "src_url": "https://live.eqtiming.com", "created_date": "2024-02-27 13:45:20", "updated_date": "2024-02-27 13:45:20", "id": "asics-sentrumsløpet-2024_20240427_httpsliveeqtimingcom", "extract_id": "40ce85b6-a7fc-433a-8bcf-75a728db94ec"}, {"date": "20240430", "type": "road", "name": "Gateløp", "distance": "Omgang 1", "distance_m": [], "place": "Ripateigane i Ørsta, NOR", "organizer": "Ørsta IL friidrett", "website": "", "website_ai_fallback": "Gateløp", "src_url": "https://live.eqtiming.com", "created_date": "2024-02-27 13:45:21", "updated_date": "2024-02-27 13:45:21", "id": "gateløp_20240430_httpsliveeqtimingcom", "extract_id": "abe67b39-92b3-405a-a239-0a6cd60c0450"}, {"date": "20240501", "type": "road", "name": "Ulfstindmila", "distance": "Omgang 1", "distance_m": [], "place": "Tønsvikbru , NOR", "organizer": "Idrettslaget Ulfstind", "website": "", "website_ai_fallback": "Ulfstindmila", "src_url": "https://live.eqtiming.com", "created_date": "2024-02-27 13:45:23", "updated_date": "2024-02-27 13:45:23", "id": "ulfstindmila_20240501_httpsliveeqtimingcom", "extract_id": "eb7e8650-75ea-4462-a569-2dd8cac8d545"}, {"date": "20240501", "type": "road", "name": "Strandløpet", "distance": "Strandløpet", "distance_m": [], "place": "Salangshallen, NOR", "organizer": "Salangen IF - Friidrett", "website": "", "website_ai_fallback": "Strandløpet", "src_url": "https://live.eqtiming.com", "created_date": "2024-02-27 13:45:24", "updated_date": "2024-02-27 13:45:24", "id": "strandløpet_20240501_httpsliveeqtimingcom", "extract_id": "d9c3171b-34cb-42de-9ecf-89839f8787e7"}, {"date": "20240501", "type": "road", "name": "Grue Halvmaraton", "distance": "Halvmaraton, 10km, Barneløp", "distance_m": [21097], "place": "Kirkenær, NOR", "organizer": "Grue IL", "website": "", "website_ai_fallback": "Grue Halvmaraton", "src_url": "https://live.eqtiming.com", "created_date": "2024-02-27 13:45:25", "updated_date": "2024-02-27 13:45:25", "id": "grue-halvmaraton_20240501_httpsliveeqtimingcom", "extract_id": "b6827008-ad8f-4853-8caa-5ad1c0a4870c"}, {"date": "20240504", "type": "road", "name": "Sunnhordland løpsfest 2024", "distance": "Halvmaraton, 10 km, 5 km, Superløpet", "distance_m": [21097, 10000, 5000], "place": "Leirvik, NOR", "organizer": "Stord IL", "website": "https://www.sunnhordlandmaraton.no/", "website_ai_fallback": "Sunnhordland løpsfest 2024", "src_url": "https://live.eqtiming.com", "created_date": "2024-02-27 13:45:27", "updated_date": "2024-02-27 13:45:27", "id": "sunnhordland-løpsfest-2024_20240504_httpsliveeqtimingcom", "extract_id": "f8a3925a-0cfa-478c-8811-9793b2f9df3a"}, {"date": "20240507", "type": "road", "name": "Tordenskioldsløpet 2024", "distance": "Omgang 1", "distance_m": [], "place": "Trondheim, NOR", "organizer": "Freidig", "website": "", "website_ai_fallback": "Tordenskioldsløpet 2024", "src_url": "https://live.eqtiming.com", "created_date": "2024-02-27 13:45:29", "updated_date": "2024-02-27 13:45:29", "id": "tordenskioldsløpet-2024_20240507_httpsliveeqtimingcom", "extract_id": "c377bc9e-40c8-49aa-9cff-052b2eac1d17"}, {"date": "20240509", "type": "road", "name": "Brurunden - Kjell Halvarssons Minneløp 2024", "distance": "Barneløp, Brurunden trim u/tid, Brurunden", "distance_m": [], "place": "Namsos / Spillum, NOR", "organizer": "Namdal løpeklubb", "website": "", "website_ai_fallback": "Brurunden - Kjell Halvarssons Minneløp 2024", "src_url": "https://live.eqtiming.com", "created_date": "2024-02-27 13:45:30", "updated_date": "2024-02-27 13:45:30", "id": "brurunden-kjell-halvarssons-minneløp-2024_20240509_httpsliveeqtimingcom", "extract_id": "3b6f4f78-ead5-4c25-88f3-ea31a61f1f7e"}, {"date": "20240509", "type": "road", "name": "Perseløpet 5km, 10km, halvmaraton  9.mai", "distance": "5km, 10km, Halvmaraton", "distance_m": [21097], "place": "Ås skole, Hammerås, Eidsvoll, NOR", "organizer": "Feiring IL", "website": "http://www.xn--perselpet-q8a.com/", "website_ai_fallback": "Perseløpet 5km, 10km, halvmaraton  9.mai", "src_url": "https://live.eqtiming.com", "created_date": "2024-02-27 13:45:32", "updated_date": "2024-02-27 13:45:32", "id": "perseløpet-5km-10km-halvmaraton-9mai_20240509_httpsliveeqtimingcom", "extract_id": "2590e417-9ace-4371-9097-13f44f5bdfad"}, {"date": "20240509", "type": "road", "name": "Åsaneløpet 2024", "distance": "5 km, 10 km, Barneløpet", "distance_m": [5000, 10000], "place": "Åsane Storsenter, NOR", "organizer": "Norna-Salhus IL", "website": "https://asanelopet.no/", "website_ai_fallback": "Åsaneløpet 2024", "src_url": "https://live.eqtiming.com", "created_date": "2024-02-27 13:45:34", "updated_date": "2024-02-27 13:45:34", "id": "åsaneløpet-2024_20240509_httpsliveeqtimingcom", "extract_id": "4d93e28f-214d-4fde-bcdf-9f7d4d0f409d"}, {"date": "20240511", "type": "road", "name": "4625løpet", "distance": "4625 løpet", "distance_m": [], "place": "Flekkerøy, NOR", "organizer": "Flekkerøy Løpeklubb", "website": "http://4625lopet.no/", "website_ai_fallback": "4625løpet", "src_url": "https://live.eqtiming.com", "created_date": "2024-02-27 13:45:35", "updated_date": "2024-02-27 13:45:35", "id": "4625løpet_20240511_httpsliveeqtimingcom", "extract_id": "b7e785d0-5119-4e82-a0e4-7881e5c95f0c"}, {"date": "20240511", "type": "road", "name": "Vårslippløpet 2024", "distance": "Vårslipp 1,5 K, Vårslipp 4,3 K TRIM, Vårslippløp 5 K, VårslippMILA, 10K", "distance_m": [5000], "place": "Tana, NOR", "organizer": "Sirma IL", "website": "", "website_ai_fallback": "Vårslippløpet 2024", "src_url": "https://live.eqtiming.com", "created_date": "2024-02-27 13:45:37", "updated_date": "2024-02-27 13:45:37", "id": "vårslippløpet-2024_20240511_httpsliveeqtimingcom", "extract_id": "4c584713-c0d4-4872-9682-e65b4bff0bc7"}, {"date": "20240516", "type": "road", "name": "Norgestesten løp 2", "distance": "5 km, 10 km, Halvmaraton", "distance_m": [5000, 10000, 21097], "place": "Jessheim, NOR", "organizer": "Ullensaker/Kisa IL", "website": "https://norgestesten.no/", "website_ai_fallback": "Norgestesten løp 2", "src_url": "https://live.eqtiming.com", "created_date": "2024-02-27 13:45:38", "updated_date": "2024-02-27 13:45:38", "id": "norgestesten-løp-2_20240516_httpsliveeqtimingcom", "extract_id": "5739f680-25ee-442a-9233-f58909d20d96"}, {"date": "20240525", "type": "road", "name": "NM Halvmaraton", "distance": "NM Halvmaraton, Åpent Halvmaraton, Tveide Rundt 10km", "distance_m": [], "place": "Birkeland, NOR", "organizer": "Birkenes IL", "website": "", "website_ai_fallback": "NM Halvmaraton", "src_url": "https://live.eqtiming.com", "created_date": "2024-02-27 13:45:40", "updated_date": "2024-02-27 13:45:40", "id": "nm-halvmaraton_20240525_httpsliveeqtimingcom", "extract_id": "30ba619a-e90e-424e-ab15-8261203ec065"}, {"date": "20240525", "type": "road", "name": "Nidaros Løpefest 2024", "distance": "10 km, 5 km", "distance_m": [10000, 5000], "place": "Skansen, NOR", "organizer": "Strindheim IL", "website": "", "website_ai_fallback": "Nidaros Løpefest 2024", "src_url": "https://live.eqtiming.com", "created_date": "2024-02-27 13:45:41", "updated_date": "2024-02-27 13:45:41", "id": "nidaros-løpefest-2024_20240525_httpsliveeqtimingcom", "extract_id": "0310c1db-983a-4809-8361-85fab1630cd0"}, {"date": "20240525", "type": "road", "name": "SpareBank 1 Vartdalsstranda Halvmaraton 2024", "distance": "Halvmaraton 21.1Km, Trimløp rundt dalen, 10 Km, KM Halvmaraton 21.1Km", "distance_m": [10000], "place": "Vartdal, NOR", "organizer": "Ørsta IL", "website": "", "website_ai_fallback": "SpareBank 1 Vartdalsstranda Halvmaraton 2024", "src_url": "https://live.eqtiming.com", "created_date": "2024-02-27 13:45:43", "updated_date": "2024-02-27 13:45:43", "id": "sparebank-1-vartdalsstranda-halvmaraton-2024_20240525_httpsliveeqtimingcom", "extract_id": "0d5e4c7d-15c5-4c21-ac95-8472a9c39a76"}, {"date": "20240525", "type": "road", "name": "Graabeinløpet", "distance": ", , ", "distance_m": [], "place": null, "organizer": null, "website": "", "website_ai_fallback": "Graabeinløpet", "src_url": "https://live.eqtiming.com", "created_date": "2024-02-27 13:45:45", "updated_date": "2024-02-27 13:45:45", "id": "graabeinløpet_20240525_httpsliveeqtimingcom", "extract_id": "6db5ba57-4f9d-43ef-883b-b6e4eccd9383"}, {"date": "20240526", "type": "road", "name": "Totenvikaløpet 2024", "distance": "Totenvikaløpet 10 km", "distance_m": [10000], "place": "Totenvika, Skreia, NOR", "organizer": "Skreia IL", "website": "https://www.facebook.com/totenvikalopet", "website_ai_fallback": "Totenvikaløpet 2024", "src_url": "https://live.eqtiming.com", "created_date": "2024-02-27 13:45:48", "updated_date": "2024-02-27 13:45:48", "id": "totenvikaløpet-2024_20240526_httpsliveeqtimingcom", "extract_id": "66c2b379-7044-4c02-a95f-243e31dbecd8"}, {"date": "20240529", "type": "road", "name": "Bykarusellen 2024 Perseløp 2 (24. mai 5 km)", "distance": "5km", "distance_m": [5000], "place": "Bergen, NOR", "organizer": "Gular, IL", "website": "http://www.bykarusellen.no/", "website_ai_fallback": "Bykarusellen 2024 Perseløp 2 (24. mai 5 km)", "src_url": "https://live.eqtiming.com", "created_date": "2024-02-27 13:45:49", "updated_date": "2024-02-27 13:45:49", "id": "bykarusellen-2024-perseløp-2-24-mai-5-km_20240529_httpsliveeqtimingcom", "extract_id": "36b004bc-4b73-4e3d-add8-6a7e6010e84c"}, {"date": "20240529", "type": "road", "name": "Jentebølgen", "distance": "5 km, Jentebølgen", "distance_m": [5000], "place": "Drammen, NOR", "organizer": "Sturla IF", "website": "", "website_ai_fallback": "Jentebølgen", "src_url": "https://live.eqtiming.com", "created_date": "2024-02-27 13:45:51", "updated_date": "2024-02-27 13:45:51", "id": "jentebølgen_20240529_httpsliveeqtimingcom", "extract_id": "094c0dcd-75d6-4c1e-a74f-e605932f4d63"}, {"date": "20240601", "type": "road", "name": "Sommernattsløpet_2024", "distance": "løp", "distance_m": [10000, 10000, 21097], "place": "Koengen, Bergen, NOR", "organizer": "Fyllingen IL", "website": "", "website_ai_fallback": "Sommernattsløpet_2024", "src_url": "https://live.eqtiming.com", "created_date": "2024-02-27 13:45:52", "updated_date": "2024-02-27 13:45:52", "id": "sommernattsløpet_2024_20240601_httpsliveeqtimingcom", "extract_id": "1d207aa2-d6a6-4c2a-9f12-c2bf92181b7f"}, {"date": "20240601", "type": "road", "name": "Fløymila 2024", "distance": "Fløymila, Fløy 5 km, Barneløpet, Dobbel", "distance_m": [5000], "place": "Flekkerøy, NOR", "organizer": "Flekkerøy Løpeklubb", "website": "https://www.facebook.com/floymila", "website_ai_fallback": "Fløymila 2024", "src_url": "https://live.eqtiming.com", "created_date": "2024-02-27 13:45:55", "updated_date": "2024-02-27 13:45:55", "id": "fløymila-2024_20240601_httpsliveeqtimingcom", "extract_id": "f4093753-8e95-4592-a02d-9bdef467d37b"}, {"date": "20240602", "type": "road", "name": "Årungen rundt", "distance": "Storplena Rundt 0,5, Storplena Rundt 1.0, Storplena Rundt 1,5", "distance_m": [], "place": "NMBU-parken, Ås, NOR", "organizer": "Ås IL", "website": "", "website_ai_fallback": "Årungen rundt", "src_url": "https://live.eqtiming.com", "created_date": "2024-02-27 13:45:57", "updated_date": "2024-02-27 13:45:57", "id": "årungen-rundt_20240602_httpsliveeqtimingcom", "extract_id": "5d238f11-4c60-42c5-a683-18d6a5338c6c"}, {"date": "20240602", "type": "road", "name": "Rekordmila 2024", "distance": "Rekordmila 2024", "distance_m": [5000, 10000], "place": "Buvika, NOR", "organizer": "Børsa IL", "website": "http://rekordmila.no/", "website_ai_fallback": "Rekordmila 2024", "src_url": "https://live.eqtiming.com", "created_date": "2024-02-27 13:45:58", "updated_date": "2024-02-27 13:45:58", "id": "rekordmila-2024_20240602_httpsliveeqtimingcom", "extract_id": "b534ceaf-7ecf-41ea-8229-818571b3de1a"}, {"date": "20240602", "type": "road", "name": "Lustraløpet 2024", "distance": "", "distance_m": [], "place": null, "organizer": null, "website": "", "website_ai_fallback": "Lustraløpet 2024", "src_url": "https://live.eqtiming.com", "created_date": "2024-02-27 13:45:59", "updated_date": "2024-02-27 13:45:59", "id": "lustraløpet-2024_20240602_httpsliveeqtimingcom", "extract_id": "e3af5fcd-9c16-4187-af63-6380221ee304"}, {"date": "20240602", "type": "road", "name": "Jessheim Halvmaraton 2024", "distance": "Halvmaraton, 5 KM", "distance_m": [21097, 5000], "place": "Jessheim, NOR", "organizer": "Ullensaker/Kisa IL", "website": "", "website_ai_fallback": "Jessheim Halvmaraton 2024", "src_url": "https://live.eqtiming.com", "created_date": "2024-02-27 13:46:04", "updated_date": "2024-02-27 13:46:04", "id": "jessheim-halvmaraton-2024_20240602_httpsliveeqtimingcom", "extract_id": "92d3a0e7-55ec-4e53-93d7-18024fec9418"}, {"date": "20240604", "type": "road", "name": "Jentebølgen 2024", "distance": "5 KM", "distance_m": [5000], "place": "Trondheim, NOR", "organizer": "Strindheim IL", "website": "", "website_ai_fallback": "Jentebølgen 2024", "src_url": "https://live.eqtiming.com", "created_date": "2024-02-27 13:46:06", "updated_date": "2024-02-27 13:46:06", "id": "jentebølgen-2024_20240604_httpsliveeqtimingcom", "extract_id": "4487acb6-330d-4487-bbad-afd40e2a9808"}, {"date": "20240605", "type": "road", "name": "OBOS Fornebuløpet 2024", "distance": "3 km, 5 km, 10 km", "distance_m": [3000, 5000, 10000], "place": ", NOR", "organizer": "Tyrving IL", "website": "http://www.fornebulopet.no/", "website_ai_fallback": "OBOS Fornebuløpet 2024", "src_url": "https://live.eqtiming.com", "created_date": "2024-02-27 13:46:08", "updated_date": "2024-02-27 13:46:08", "id": "obos-fornebuløpet-2024_20240605_httpsliveeqtimingcom", "extract_id": "a5d4bc34-b76c-4ed3-88b7-715cf0dd8f35"}, {"date": "20240608", "type": "road", "name": "The Arctic Run", "distance": "Maraton, Halv-Maraton, 10km", "distance_m": [42195], "place": "Hadsel, NOR", "organizer": "Stokmarknes IL", "website": "https://thearcticrun.com/no/", "website_ai_fallback": "The Arctic Run", "src_url": "https://live.eqtiming.com", "created_date": "2024-02-27 13:46:10", "updated_date": "2024-02-27 13:46:10", "id": "the-arctic-run_20240608_httpsliveeqtimingcom", "extract_id": "f8ae98b4-6dd0-48a3-970d-faee79ef3e7a"}, {"date": "20240608", "type": "road", "name": "BERGEN3000: Store Lungegårdsvannet rundt, 08.06.2024", "distance": "3000 m, 3000 m barn (0-13 år), 3000 m paraklasser, 3000 m paraklasse barn (0-13 år)", "distance_m": [3000000, 3000000], "place": "Bergen, NOR", "organizer": "Sædalen Idrettslag", "website": "http://bergen3000.no/", "website_ai_fallback": "BERGEN3000: Store Lungegårdsvannet rundt, 08.06.2024", "src_url": "https://live.eqtiming.com", "created_date": "2024-02-27 13:46:11", "updated_date": "2024-02-27 13:46:11", "id": "bergen3000-store-lungegårdsvannet-rundt-08062024_20240608_httpsliveeqtimingcom", "extract_id": "e41b3dfa-245e-42c5-a698-566ebdb6dceb"}, {"date": "20240609", "type": "road", "name": "Norgestesten løp 3", "distance": "5 km, 10 km", "distance_m": [5000, 10000], "place": "Jessheim, NOR", "organizer": "Ullensaker/Kisa IL", "website": "https://norgestesten.no/", "website_ai_fallback": "Norgestesten løp 3", "src_url": "https://live.eqtiming.com", "created_date": "2024-02-27 13:46:13", "updated_date": "2024-02-27 13:46:13", "id": "norgestesten-løp-3_20240609_httpsliveeqtimingcom", "extract_id": "13a74b1f-8b11-429a-a575-70646c2d2a64"}, {"date": "20240615", "type": "road", "name": "Anton Sport Sommerløpet", "distance": "Barneløp, 3 km folkeløp, 5 km", "distance_m": [3000, 5000], "place": "Kristiansand, NOR", "organizer": "Kristiansand Løpeklubb", "website": "", "website_ai_fallback": "Anton Sport Sommerløpet", "src_url": "https://live.eqtiming.com", "created_date": "2024-02-27 13:46:15", "updated_date": "2024-02-27 13:46:15", "id": "anton-sport-sommerløpet_20240615_httpsliveeqtimingcom", "extract_id": "8be66a5d-529c-4065-9793-664391c54b45"}, {"date": "20240622", "type": "road", "name": "NM Maraton 2024 - Knarvik marathon", "distance": "Marathon, Halvmarathon", "distance_m": [42195], "place": "Knarvik, NOR", "organizer": "Fil Aks-77", "website": "", "website_ai_fallback": "NM Maraton 2024 - Knarvik marathon", "src_url": "https://live.eqtiming.com", "created_date": "2024-02-27 13:46:16", "updated_date": "2024-02-27 13:46:16", "id": "nm-maraton-2024-knarvik-marathon_20240622_httpsliveeqtimingcom", "extract_id": "ef82e807-633b-4532-a522-a27a3704fd01"}, {"date": "20240622", "type": "road", "name": "Midnight Sun Marathon 2024", "distance": "Mizuno Halvmaraton, Maraton, Coop Mila (10km)", "distance_m": [42195], "place": "Tromsø, NOR", "organizer": "TUIL Tromsdalen Friidrett", "website": "http://%20http//www.msm.no/", "website_ai_fallback": "Midnight Sun Marathon 2024", "src_url": "https://live.eqtiming.com", "created_date": "2024-02-27 13:46:18", "updated_date": "2024-02-27 13:46:18", "id": "midnight-sun-marathon-2024_20240622_httpsliveeqtimingcom", "extract_id": "9ebbe3f4-57d9-4302-8871-9aa1fd9c6300"}, {"date": "20240623", "type": "road", "name": "Perseløpet 5km, 10km, halvmaraton  23. juni", "distance": "5km, 10km, Halvmaraton", "distance_m": [21097], "place": "Ås skole, Hammerås, Eidsvoll, NOR", "organizer": "Feiring IL", "website": "http://www.xn--perselpet-q8a.com/", "website_ai_fallback": "Perseløpet 5km, 10km, halvmaraton  23. juni", "src_url": "https://live.eqtiming.com", "created_date": "2024-02-27 13:46:20", "updated_date": "2024-02-27 13:46:20", "id": "perseløpet-5km-10km-halvmaraton-23-juni_20240623_httpsliveeqtimingcom", "extract_id": "8dfe36d8-0792-4065-b3e8-a997411fad58"}, {"date": "20240625", "type": "road", "name": "Norgestesten løp 4", "distance": "5 km, 10 km, Halvmaraton", "distance_m": [5000, 10000, 21097], "place": "Jessheim, NOR", "organizer": "Ullensaker/Kisa IL", "website": "https://norgestesten.no/", "website_ai_fallback": "Norgestesten løp 4", "src_url": "https://live.eqtiming.com", "created_date": "2024-02-27 13:46:22", "updated_date": "2024-02-27 13:46:22", "id": "norgestesten-løp-4_20240625_httpsliveeqtimingcom", "extract_id": "e6a20404-01df-41af-93dc-cbffa8eb4997"}, {"date": "20240703", "type": "road", "name": "Sjøvegan minimaraton", "distance": "", "distance_m": [], "place": "Sjøvegan, NOR", "organizer": "Salangen IF - Friidrett", "website": "", "website_ai_fallback": "Sjøvegan minimaraton", "src_url": "https://live.eqtiming.com", "created_date": "2024-02-27 13:46:23", "updated_date": "2024-02-27 13:46:23", "id": "sjøvegan-minimaraton_20240703_httpsliveeqtimingcom", "extract_id": "a814eedb-bbfe-4ea4-bf85-3e769db25357"}, {"date": "20240706", "type": "road", "name": "Perseløpet  ultra", "distance": "50km, 100km", "distance_m": [], "place": "Ås skole, Hammerås, Eidsvoll, NOR", "organizer": "Feiring IL", "website": "http://www.xn--perselpet-q8a.com/", "website_ai_fallback": "Perseløpet  ultra", "src_url": "https://live.eqtiming.com", "created_date": "2024-02-27 13:46:25", "updated_date": "2024-02-27 13:46:25", "id": "perseløpet-ultra_20240706_httpsliveeqtimingcom", "extract_id": "ffe2f050-e272-4a88-a69e-5ce395b2e79e"}, {"date": "20240727", "type": "road", "name": "Hornindalsvatnet Maraton 2024", "distance": "Maraton, Halvmaraton, 10 km", "distance_m": [10000, 21097, 42195], "place": "Hornindal Idrettspark, NOR", "organizer": "Hornindal IL", "website": "http://iahaugen.no/maraton/", "website_ai_fallback": "Hornindalsvatnet Maraton 2024", "src_url": "https://live.eqtiming.com", "created_date": "2024-02-27 13:46:26", "updated_date": "2024-02-27 13:46:26", "id": "hornindalsvatnet-maraton-2024_20240727_httpsliveeqtimingcom", "extract_id": "8ebfe496-5c4f-4032-953f-7592c7ed8c0c"}, {"date": "20240804", "type": "road", "name": "Perseløpet 5km, 10km, halvmaraton  4 aug", "distance": "5km, 10km, Halvmaraton", "distance_m": [21097], "place": "Ås skole, Hammerås, Eidsvoll, NOR", "organizer": "Feiring IL", "website": "http://www.xn--perselpet-q8a.com/", "website_ai_fallback": "Perseløpet 5km, 10km, halvmaraton  4 aug", "src_url": "https://live.eqtiming.com", "created_date": "2024-02-27 13:46:30", "updated_date": "2024-02-27 13:46:30", "id": "perseløpet-5km-10km-halvmaraton-4-aug_20240804_httpsliveeqtimingcom", "extract_id": "b21499bc-6f7a-4c3a-a447-0da7edf74bb5"}, {"date": "20240807", "type": "road", "name": "Orkland Energimila 2024", "distance": "5 km, 10 km", "distance_m": [4000, 5000, 10000, 10000], "place": "Orkanger, NOR", "organizer": "Orkanger IF - Friidrett", "website": "", "website_ai_fallback": "Orkland Energimila 2024", "src_url": "https://live.eqtiming.com", "created_date": "2024-02-27 13:46:32", "updated_date": "2024-02-27 13:46:32", "id": "orkland-energimila-2024_20240807_httpsliveeqtimingcom", "extract_id": "a7bc70a1-8e86-401e-b2dc-a0daa008f744"}, {"date": "20240810", "type": "road", "name": "Bodø Run Festival 2024", "distance": "Sport1 5 km, AN mila, Nordasfalt Halvmaraton, Etapper - AN mila", "distance_m": [5000], "place": null, "organizer": null, "website": "", "website_ai_fallback": "Bodø Run Festival 2024", "src_url": "https://live.eqtiming.com", "created_date": "2024-02-27 13:46:35", "updated_date": "2024-02-27 13:46:35", "id": "bodø-run-festival-2024_20240810_httpsliveeqtimingcom", "extract_id": "5ef137ae-4d93-4cd3-8085-4859c3b7006e"}, {"date": "20240817", "type": "road", "name": "SAMI MARATON 2024", "distance": "VårEnergi MILA, 10K, RUN4FUN, 5 km trim, HALVMARATON, MARATON", "distance_m": [], "place": "Tanabru og omegn (Start Per Fokstadgeaidnu 60), NOR", "organizer": "Sirma IL", "website": "https://samimaraton.no/", "website_ai_fallback": "SAMI MARATON 2024", "src_url": "https://live.eqtiming.com", "created_date": "2024-02-27 13:46:38", "updated_date": "2024-02-27 13:46:38", "id": "sami-maraton-2024_20240817_httpsliveeqtimingcom", "extract_id": "ed41c7f6-6775-4f7c-87e2-72fa1119451f"}, {"date": "20240818", "type": "road", "name": "Norgestesten løp 5", "distance": "5 km, 10 km, Halvmaraton", "distance_m": [5000, 10000, 21097], "place": "Jessheim, NOR", "organizer": "Ullensaker/Kisa IL", "website": "https://norgestesten.no/", "website_ai_fallback": "Norgestesten løp 5", "src_url": "https://live.eqtiming.com", "created_date": "2024-02-27 13:46:39", "updated_date": "2024-02-27 13:46:39", "id": "norgestesten-løp-5_20240818_httpsliveeqtimingcom", "extract_id": "251d0699-2511-4144-b0bf-7bbdcc400d3b"}, {"date": "20240818", "type": "road", "name": "LyngenMila", "distance": "Omgang 1", "distance_m": [], "place": "Lyngen, NOR", "organizer": "Lyngen/Karnes IL", "website": "", "website_ai_fallback": "LyngenMila", "src_url": "https://live.eqtiming.com", "created_date": "2024-02-27 13:46:41", "updated_date": "2024-02-27 13:46:41", "id": "lyngenmila_20240818_httpsliveeqtimingcom", "extract_id": "6ac7aa01-737c-4ef8-8ff4-c9a856e4e2c3"}, {"date": "20240821", "type": "road", "name": "BIP løpet-2024", "distance": "BIP-løpet 5 km", "distance_m": [5000], "place": "Rud, Bærum, NOR", "organizer": "Tyrving IL", "website": "", "website_ai_fallback": "BIP løpet-2024", "src_url": "https://live.eqtiming.com", "created_date": "2024-02-27 13:46:42", "updated_date": "2024-02-27 13:46:42", "id": "bip-løpet-2024_20240821_httpsliveeqtimingcom", "extract_id": "402ffa4a-6182-48e3-b856-9001f8eaa8c6"}, {"date": "20240831", "type": "road", "name": "Stavanger Marathon 2024", "distance": "Maraton, Halvmaraton, 5 km", "distance_m": [42195, 21097, 5000], "place": "Stavanger, NOR", "organizer": "GTI Friidrettsklubb", "website": "https://stavangermarathon.no/", "website_ai_fallback": "Stavanger Marathon 2024", "src_url": "https://live.eqtiming.com", "created_date": "2024-02-27 13:46:45", "updated_date": "2024-02-27 13:46:45", "id": "stavanger-marathon-2024_20240831_httpsliveeqtimingcom", "extract_id": "7960c303-62fb-4adb-abbd-aa4a6758afd6"}, {"date": "20240901", "type": "road", "name": "Norgestesten løp 6", "distance": "5 km, 10 km, Halvmaraton", "distance_m": [5000, 10000, 21097], "place": "Jessheim, NOR", "organizer": "Ullensaker/Kisa IL", "website": "https://norgestesten.no/", "website_ai_fallback": "Norgestesten løp 6", "src_url": "https://live.eqtiming.com", "created_date": "2024-02-27 13:46:47", "updated_date": "2024-02-27 13:46:47", "id": "norgestesten-løp-6_20240901_httpsliveeqtimingcom", "extract_id": "17174e89-109f-48dd-aece-0a8c88938112"}, {"date": "20240901", "type": "road", "name": "Perseløpet 5km, 10km, halvmaraton  1.sept", "distance": "5km, 10km, Halvmaraton", "distance_m": [21097], "place": "Ås skole, Hammerås, Eidsvoll, NOR", "organizer": "Feiring IL", "website": "http://www.xn--perselpet-q8a.com/", "website_ai_fallback": "Perseløpet 5km, 10km, halvmaraton  1.sept", "src_url": "https://live.eqtiming.com", "created_date": "2024-02-27 13:46:48", "updated_date": "2024-02-27 13:46:48", "id": "perseløpet-5km-10km-halvmaraton-1sept_20240901_httpsliveeqtimingcom", "extract_id": "58316d56-9fd4-4c69-b933-2a6b276fab41"}, {"date": "20240904", "type": "road", "name": "Bykarusellen 2024 Perseløp 3 (4. september 5 km)", "distance": "5km", "distance_m": [], "place": "Bergen, NOR", "organizer": "Gular, IL", "website": "http://www.bykarusellen.no/", "website_ai_fallback": "Bykarusellen 2024 Perseløp 3 (4. september 5 km)", "src_url": "https://live.eqtiming.com", "created_date": "2024-02-27 13:46:50", "updated_date": "2024-02-27 13:46:50", "id": "bykarusellen-2024-perseløp-3-4-september-5-km_20240904_httpsliveeqtimingcom", "extract_id": "0ca7890b-702d-4a4f-b7aa-b40e368f8a52"}, {"date": "20240906", "type": "road", "name": "Knarvikmila 2024", "distance": "10 km, Naturmila Familie, Halvmarathon, Naturmila", "distance_m": [10000], "place": "Knarvik Stadion, NOR", "organizer": "Fil Aks-77", "website": "http://www.knarvikmila.no/", "website_ai_fallback": "Knarvikmila 2024", "src_url": "https://live.eqtiming.com", "created_date": "2024-02-27 13:46:52", "updated_date": "2024-02-27 13:46:52", "id": "knarvikmila-2024_20240906_httpsliveeqtimingcom", "extract_id": "83edfbd2-bfd4-40ff-95c5-88d60950168e"}, {"date": "20240907", "type": "road", "name": "Smili 2024", "distance": "Omgang 1", "distance_m": [], "place": "Sogndal, NOR", "organizer": "Sogndal IL", "website": "", "website_ai_fallback": "Smili 2024", "src_url": "https://live.eqtiming.com", "created_date": "2024-02-27 13:46:54", "updated_date": "2024-02-27 13:46:54", "id": "smili-2024_20240907_httpsliveeqtimingcom", "extract_id": "99a4f7d4-c10b-4540-983c-fe608df34fa0"}, {"date": "20240908", "type": "road", "name": "Drammen halvmaraton 2024", "distance": "Omgang 1", "distance_m": [], "place": ", NOR", "organizer": "Sturla IF", "website": "", "website_ai_fallback": "Drammen halvmaraton 2024", "src_url": "https://live.eqtiming.com", "created_date": "2024-02-27 13:46:55", "updated_date": "2024-02-27 13:46:55", "id": "drammen-halvmaraton-2024_20240908_httpsliveeqtimingcom", "extract_id": "b0392273-f23f-4abe-8bea-d8bd5c603afd"}, {"date": "20240908", "type": "road", "name": "Bybaneløpet 2024", "distance": "Bybaneløpet 10 km", "distance_m": [10000], "place": "Nesttun - Bergen, NOR", "organizer": "Fana IL", "website": "", "website_ai_fallback": "Bybaneløpet 2024", "src_url": "https://live.eqtiming.com", "created_date": "2024-02-27 13:46:57", "updated_date": "2024-02-27 13:46:57", "id": "bybaneløpet-2024_20240908_httpsliveeqtimingcom", "extract_id": "57afa641-7a96-44f5-a816-92e60fd27d83"}, {"date": "20240914", "type": "road", "name": "Fjordkraft Bergen City Milen 2024", "distance": "Omgang 1", "distance_m": [], "place": ", NOR", "organizer": "Viking, TIF", "website": "", "website_ai_fallback": "Fjordkraft Bergen City Milen 2024", "src_url": "https://live.eqtiming.com", "created_date": "2024-02-27 13:46:59", "updated_date": "2024-02-27 13:46:59", "id": "fjordkraft-bergen-city-milen-2024_20240914_httpsliveeqtimingcom", "extract_id": "be8fa9a9-0905-4872-84f0-9650e505c754"}, {"date": "20240915", "type": "road", "name": "Lina Roindt 2024", "distance": "10,8 km", "distance_m": [10000], "place": "Rindal, NOR", "organizer": "Rindal IL", "website": "", "website_ai_fallback": "Lina Roindt 2024", "src_url": "https://live.eqtiming.com", "created_date": "2024-02-27 13:47:01", "updated_date": "2024-02-27 13:47:01", "id": "lina-roindt-2024_20240915_httpsliveeqtimingcom", "extract_id": "ef2c9cba-762c-474d-bc35-96c1a89bf651"}, {"date": "20240915", "type": "road", "name": "Perseløpet 5km, 10km, halvmaraton  15.sept", "distance": "5km, 10km, Halvmaraton", "distance_m": [21097], "place": "Ås skole, Hammerås, Eidsvoll, NOR", "organizer": "Feiring IL", "website": "http://www.xn--perselpet-q8a.com/", "website_ai_fallback": "Perseløpet 5km, 10km, halvmaraton  15.sept", "src_url": "https://live.eqtiming.com", "created_date": "2024-02-27 13:47:02", "updated_date": "2024-02-27 13:47:02", "id": "perseløpet-5km-10km-halvmaraton-15sept_20240915_httpsliveeqtimingcom", "extract_id": "8fc5f5e9-0d64-4737-abe6-e27370a228b3"}, {"date": "20240921", "type": "road", "name": "Romsdal 5/10/halv/hel", "distance": "5 km, 10 km, Halvmaraton, Maraton", "distance_m": [5000, 10000, 21097, 42195], "place": "Hustadvika, NOR", "organizer": "Molde og Omegn IF", "website": "https://www.romsdal510halv.no/", "website_ai_fallback": "Romsdal 5/10/halv/hel", "src_url": "https://live.eqtiming.com", "created_date": "2024-02-27 13:47:04", "updated_date": "2024-02-27 13:47:04", "id": "romsdal-510halvhel_20240921_httpsliveeqtimingcom", "extract_id": "5564faa9-0532-448e-8b6d-7df24e12444a"}, {"date": "20240921", "type": "road", "name": "BMW Oslo Maraton 2024", "distance": "Maraton, Halvmaraton, 10 for Grete", "distance_m": [21097, 21097, 42195, 42195], "place": "Oslo, NOR", "organizer": "Sportsklubben Vidar", "website": "https://oslomaraton.no/", "website_ai_fallback": "BMW Oslo Maraton 2024", "src_url": "https://live.eqtiming.com", "created_date": "2024-02-27 13:47:06", "updated_date": "2024-02-27 13:47:06", "id": "bmw-oslo-maraton-2024_20240921_httpsliveeqtimingcom", "extract_id": "68b41eb9-ad22-414c-8a85-01c81ef4261d"}, {"date": "20240921", "type": "road", "name": "Flyplassmila 2024 (Stord Lufthamn)", "distance": "5km, 10km", "distance_m": [], "place": "Sørstokken , NOR", "organizer": "Stord IL", "website": "", "website_ai_fallback": "Flyplassmila 2024 (Stord Lufthamn)", "src_url": "https://live.eqtiming.com", "created_date": "2024-02-27 13:47:09", "updated_date": "2024-02-27 13:47:09", "id": "flyplassmila-2024-stord-lufthamn_20240921_httpsliveeqtimingcom", "extract_id": "2ec60ef2-fb07-489d-b315-337b7a23ac87"}, {"date": "20240922", "type": "road", "name": "Heim Halvmaraton 2024", "distance": "Halvmaraton", "distance_m": [21097], "place": "Kyrksæterøra, NOR", "organizer": "Kyrksæterøra IL", "website": "", "website_ai_fallback": "Heim Halvmaraton 2024", "src_url": "https://live.eqtiming.com", "created_date": "2024-02-27 13:47:10", "updated_date": "2024-02-27 13:47:10", "id": "heim-halvmaraton-2024_20240922_httpsliveeqtimingcom", "extract_id": "03b32347-26d9-4c6c-a46c-ef441ea241b5"}, {"date": "20240925", "type": "road", "name": "Bykarusellen 2024 Perseløp 4 (25. september 5 & 10 km)", "distance": "5km, 10km", "distance_m": [], "place": "Bergen, NOR", "organizer": "Gular, IL", "website": "http://www.bykarusellen.no/", "website_ai_fallback": "Bykarusellen 2024 Perseløp 4 (25. september 5 & 10 km)", "src_url": "https://live.eqtiming.com", "created_date": "2024-02-27 13:47:12", "updated_date": "2024-02-27 13:47:12", "id": "bykarusellen-2024-perseløp-4-25-september-5-10-km_20240925_httpsliveeqtimingcom", "extract_id": "80ba8e47-393e-49e2-bef9-33a7a46b3580"}, {"date": "20240925", "type": "road", "name": "Idrettsheialøpet", "distance": "Idrettsheialøpet", "distance_m": [], "place": "SJØVEGAN, NOR", "organizer": "Salangen IF - Friidrett", "website": "", "website_ai_fallback": "Idrettsheialøpet", "src_url": "https://live.eqtiming.com", "created_date": "2024-02-27 13:47:14", "updated_date": "2024-02-27 13:47:14", "id": "idrettsheialøpet_20240925_httpsliveeqtimingcom", "extract_id": "19cf08d6-fe3b-4b3b-ac32-2e3f655f9747"}, {"date": "20240928", "type": "road", "name": "Torvikbukt rundt 2024", "distance": "Torvikbukt Rundt, Torvikbukt Rundt 5,5 km", "distance_m": [], "place": "Torvikbukt, NOR", "organizer": "Torvikbukt IL", "website": "http://torvikbukt.no/", "website_ai_fallback": "Torvikbukt rundt 2024", "src_url": "https://live.eqtiming.com", "created_date": "2024-02-27 13:47:15", "updated_date": "2024-02-27 13:47:15", "id": "torvikbukt-rundt-2024_20240928_httpsliveeqtimingcom", "extract_id": "4e0a730d-01ab-4fd1-8f03-d7a5f3315d3d"}, {"date": "20240928", "type": "road", "name": "Accountor Hammerfestmila 2024", "distance": "10k, 5k, Stafett", "distance_m": [10000, 5000], "place": "Hammerfest, NOR", "organizer": "Kvalsund Arctic Runners Løpeklubb", "website": "", "website_ai_fallback": "Accountor Hammerfestmila 2024", "src_url": "https://live.eqtiming.com", "created_date": "2024-02-27 13:47:17", "updated_date": "2024-02-27 13:47:17", "id": "accountor-hammerfestmila-2024_20240928_httpsliveeqtimingcom", "extract_id": "1c212dc2-3a7b-471c-95d9-e71e83b627d1"}, {"date": "20240928", "type": "road", "name": "PB Milå 2024", "distance": "PB Milå, Sentrum Rundt Barneløp, PB 5 km", "distance_m": [5000], "place": "Randaberg, NOR", "organizer": "Grødem Runners", "website": "http://www.xn--pbmil-qra.no/", "website_ai_fallback": "PB Milå 2024", "src_url": "https://live.eqtiming.com", "created_date": "2024-02-27 13:47:19", "updated_date": "2024-02-27 13:47:19", "id": "pb-milå-2024_20240928_httpsliveeqtimingcom", "extract_id": "6700447d-ff8f-4aa4-93bf-168e11c80eaf"}, {"date": "20240928", "type": "road", "name": "Norgesløpet 2024", "distance": "10km, Ida Eides Minneløp 5 KM, Halvmaraton", "distance_m": [5000, 21097], "place": "Jessheim - Ullensaker, NOR", "organizer": "Ullensaker/Kisa IL", "website": "http://www.norgeslopet.net/", "website_ai_fallback": "Norgesløpet 2024", "src_url": "https://live.eqtiming.com", "created_date": "2024-02-27 13:47:20", "updated_date": "2024-02-27 13:47:20", "id": "norgesløpet-2024_20240928_httpsliveeqtimingcom", "extract_id": "c18d8bee-0005-4290-b91a-297c301eeea8"}, {"date": "20241001", "type": "road", "name": "Rosa sløyfe Bergen_2024", "distance": "løp", "distance_m": [], "place": "Torgallmenningen, Bergen, NOR", "organizer": "Fyllingen IL", "website": "", "website_ai_fallback": "Rosa sløyfe Bergen_2024", "src_url": "https://live.eqtiming.com", "created_date": "2024-02-27 13:47:21", "updated_date": "2024-02-27 13:47:21", "id": "rosa-sløyfe-bergen_2024_20241001_httpsliveeqtimingcom", "extract_id": "1e593cc5-64a3-4abb-b512-4aa196dd4f3f"}, {"date": "20241005", "type": "road", "name": "Gloppen Halvmaraton 2024", "distance": "Gloppen Halvmaraton 2024", "distance_m": [], "place": "Sandane, NOR", "organizer": "Fjellhug/Vereide IL", "website": "", "website_ai_fallback": "Gloppen Halvmaraton 2024", "src_url": "https://live.eqtiming.com", "created_date": "2024-02-27 13:47:23", "updated_date": "2024-02-27 13:47:23", "id": "gloppen-halvmaraton-2024_20241005_httpsliveeqtimingcom", "extract_id": "617c3f4d-1261-4fac-b386-a95e01d21dc5"}, {"date": "20241006", "type": "road", "name": "Perseløpet  5km,10km, halvmaraton, maraton og 50km_høst", "distance": "Maraton, 50km, Halvmaraton", "distance_m": [42195, 21097], "place": "Ås skole, Hammerås, Eidsvoll, NOR", "organizer": "Feiring IL", "website": "http://www.xn--perselpet-q8a.com/", "website_ai_fallback": "Perseløpet  5km,10km, halvmaraton, maraton og 50km_høst", "src_url": "https://live.eqtiming.com", "created_date": "2024-02-27 13:47:25", "updated_date": "2024-02-27 13:47:25", "id": "perseløpet-5km10km-halvmaraton-maraton-og-50km_høst_20241006_httpsliveeqtimingcom", "extract_id": "7af4514e-7467-4bf2-9f8a-50b396186799"}, {"date": "20241019", "type": "road", "name": "Hytteplanmila NM 10 km Gateløp", "distance": "Omgang 1", "distance_m": [], "place": "Trongmoen, NOR", "organizer": "Holeværingen IL", "website": "http://www.hytteplanmila.no/", "website_ai_fallback": "Hytteplanmila NM 10 km Gateløp", "src_url": "https://live.eqtiming.com", "created_date": "2024-02-27 13:47:27", "updated_date": "2024-02-27 13:47:27", "id": "hytteplanmila-nm-10-km-gateløp_20241019_httpsliveeqtimingcom", "extract_id": "710b94e1-1d70-46c9-8f14-237972df2940"}, {"date": "20241027", "type": "road", "name": "Norgestesten løp 7", "distance": "5 km, 10 km, Halvmaraton", "distance_m": [5000, 10000, 21097], "place": "Jessheim, NOR", "organizer": "Ullensaker/Kisa IL", "website": "https://norgestesten.no/", "website_ai_fallback": "Norgestesten løp 7", "src_url": "https://live.eqtiming.com", "created_date": "2024-02-27 13:47:30", "updated_date": "2024-02-27 13:47:30", "id": "norgestesten-løp-7_20241027_httpsliveeqtimingcom", "extract_id": "9ed09a2d-5804-45a1-9cee-3be2de014bb4"}, {"date": "20241027", "type": "road", "name": "Nigthrun_2024", "distance": "løp", "distance_m": [], "place": "Hordnesskogen, Bergen, NOR", "organizer": "Fyllingen IL", "website": "", "website_ai_fallback": "Nigthrun_2024", "src_url": "https://live.eqtiming.com", "created_date": "2024-02-27 13:47:31", "updated_date": "2024-02-27 13:47:31", "id": "nigthrun_2024_20241027_httpsliveeqtimingcom", "extract_id": "3bb5a8ec-4780-433b-a85c-0df6fa4e1b4c"}, {"date": "20241102", "type": "road", "name": "Barfrostløpet 2024", "distance": "Barfrost 1,5 K, Barfrost 4,3 K TRIM, Barfrostløp 5 K, BarfrostMILA, 10K", "distance_m": [5000], "place": "Tana, NOR", "organizer": "Sirma IL", "website": "", "website_ai_fallback": "Barfrostløpet 2024", "src_url": "https://live.eqtiming.com", "created_date": "2024-02-27 13:47:33", "updated_date": "2024-02-27 13:47:33", "id": "barfrostløpet-2024_20241102_httpsliveeqtimingcom", "extract_id": "17d4ffa0-feeb-4156-a2a7-05a71c1bc756"}, {"date": "20241110", "type": "road", "name": "Vintermaraton 2024", "distance": "10 km, Halvmaraton, Maraton", "distance_m": [10000, 21097, 42195], "place": "Jessheim, NOR", "organizer": "Ullensaker/Kisa IL", "website": "", "website_ai_fallback": "Vintermaraton 2024", "src_url": "https://live.eqtiming.com", "created_date": "2024-02-27 13:47:35", "updated_date": "2024-02-27 13:47:35", "id": "vintermaraton-2024_20241110_httpsliveeqtimingcom", "extract_id": "933ce7c0-124e-4055-beb7-14cff4bf66ba"}, {"date": "20250104", "type": "road", "name": "PolarNight Marathon 2025", "distance": "Half Marathon, Mørketidsmila (10km), Mørketidstrimmen (5km), Ishavskraft Marathon", "distance_m": [21097], "place": "Tromsø, NOR", "organizer": "TUIL Tromsdalen Friidrett", "website": "http://www.msm.no/", "website_ai_fallback": "PolarNight Marathon 2025", "src_url": "https://live.eqtiming.com", "created_date": "2024-02-27 13:47:36", "updated_date": "2024-02-27 13:47:36", "id": "polarnight-marathon-2025_20250104_httpsliveeqtimingcom", "extract_id": "f915eb99-cd8f-4fff-9a45-35e569484eaf"}, {"date": "20250607", "type": "road", "name": "Anton Sport Sommerløpet 2025", "distance": "Barneløp, 600 m, 3 km, 5 km", "distance_m": [3000, 5000], "place": "Kristiansand, NOR", "organizer": "Kristiansand Løpeklubb", "website": "", "website_ai_fallback": "Anton Sport Sommerløpet 2025", "src_url": "https://live.eqtiming.com", "created_date": "2024-02-27 13:47:38", "updated_date": "2024-02-27 13:47:38", "id": "anton-sport-sommerløpet-2025_20250607_httpsliveeqtimingcom", "extract_id": "f67cc086-4cfd-4901-a93d-3b5c4ceb3cab"}, {"date": "20240420", "type": "terrain", "name": "Voldsløkka Rundt - Løp 1", "distance": "6 km, 1 km barneløp", "distance_m": [6000, 1000], "place": "Oslo, NOR", "organizer": "Kamp/Vestheim IF", "website": "https://voldslokkarundt.no/", "website_ai_fallback": "Voldsløkka Rundt - Løp 1", "src_url": "https://live.eqtiming.com", "created_date": "2024-03-04 17:05:16", "updated_date": "2024-03-04 17:05:16", "id": "voldsløkka-rundt-løp-1_20240420_httpsliveeqtimingcom", "extract_id": "c3eb7130-8ae5-48c9-a72c-3c3b61b2b036"}, {"date": "20240427", "type": "terrain", "name": "Siddisløpet - Den Gule Banken løpet", "distance": "8,1 km", "distance_m": [8000], "place": "Stavanger, NOR", "organizer": "IL Skjalg", "website": "https://www.siddislopet.no/", "website_ai_fallback": "Siddisløpet - Den Gule Banken løpet", "src_url": "https://live.eqtiming.com", "created_date": "2024-03-04 17:05:20", "updated_date": "2024-03-04 17:05:20", "id": "siddisløpet-den-gule-banken-løpet_20240427_httpsliveeqtimingcom", "extract_id": "db3d06ed-0e8f-4cf5-abf5-71fa014040f6"}, {"date": "20240428", "type": "terrain", "name": "Furumo Terrengløp", "distance": "3,2 km", "distance_m": [3000], "place": ", NOR", "organizer": "Modum Friidrettsklubb", "website": "", "website_ai_fallback": "Furumo Terrengløp", "src_url": "https://live.eqtiming.com", "created_date": "2024-03-04 17:05:24", "updated_date": "2024-03-04 17:05:24", "id": "furumo-terrengløp_20240428_httpsliveeqtimingcom", "extract_id": "f8ba69e6-9d85-4896-81ed-3759080055ef"}, {"date": "20240525", "type": "terrain", "name": "Voldsløkka Rundt - Løp 2", "distance": "6 km, 1 km barneløp", "distance_m": [6000, 1000], "place": "Oslo, NOR", "organizer": "Kamp/Vestheim IF", "website": "https://voldslokkarundt.no/", "website_ai_fallback": "Voldsløkka Rundt - Løp 2", "src_url": "https://live.eqtiming.com", "created_date": "2024-03-04 17:05:29", "updated_date": "2024-03-04 17:05:29", "id": "voldsløkka-rundt-løp-2_20240525_httpsliveeqtimingcom", "extract_id": "2b9c25e3-0838-4015-91c3-d2f0cb7da3f8"}, {"date": "20240706", "type": "terrain", "name": "Rødtangen Rundt 2024", "distance": "4 km, 10 km, 15 km", "distance_m": [4000, 10000, 15000], "place": "Rødtangen, NOR", "organizer": "Holmsbu IF", "website": "http://www.holmsbuif.no/blog/post/100536/rodtangen-rundt---2017", "website_ai_fallback": "Rødtangen Rundt 2024", "src_url": "https://live.eqtiming.com", "created_date": "2024-03-04 17:05:40", "updated_date": "2024-03-04 17:05:40", "id": "rødtangen-rundt-2024_20240706_httpsliveeqtimingcom", "extract_id": "c85671ae-073b-407c-af17-058eb90ffcb0"}, {"date": "20240714", "type": "terrain", "name": "Blåfjelløpet 2024", "distance": "10 km", "distance_m": [10000], "place": "Dragset, Bøfjorden, NOR", "organizer": "Bøfjord IL", "website": "https://fb.me/e/1phlhUU9n", "website_ai_fallback": "Blåfjelløpet 2024", "src_url": "https://live.eqtiming.com", "created_date": "2024-03-04 17:05:45", "updated_date": "2024-03-04 17:05:45", "id": "blåfjelløpet-2024_20240714_httpsliveeqtimingcom", "extract_id": "df4ff957-c9d7-49ce-a836-33cc172e387e"}, {"date": "20240810", "type": "terrain", "name": "Trysilmila 2024", "distance": "Trysilmila 10km, 6,5 km, Trim uten tidtaking, barneløp", "distance_m": [6000], "place": "Østby i Trysil, NOR", "organizer": "Østby IL", "website": "", "website_ai_fallback": "Trysilmila 2024", "src_url": "https://live.eqtiming.com", "created_date": "2024-03-04 17:05:48", "updated_date": "2024-03-04 17:05:48", "id": "trysilmila-2024_20240810_httpsliveeqtimingcom", "extract_id": "b570d158-7c9d-4614-9e16-99da5fc04d7b"}, {"date": "20240825", "type": "terrain", "name": "Klempheia rundt 2024", "distance": "11 km", "distance_m": [11000], "place": "Kulørn - Kyrksæterøra, NOR", "organizer": "Kyrksæterøra IL", "website": "", "website_ai_fallback": "Klempheia rundt 2024", "src_url": "https://live.eqtiming.com", "created_date": "2024-03-04 17:05:50", "updated_date": "2024-03-04 17:05:50", "id": "klempheia-rundt-2024_20240825_httpsliveeqtimingcom", "extract_id": "d6344501-5d90-40f2-a220-10f88932217a"}, {"date": "20240907", "type": "terrain", "name": "Harstad Summits Trail Marathon 2024", "distance": "Maraton, Halvmaraton, 12km", "distance_m": [42195, 21097], "place": "Harstad, NOR", "organizer": "IK Hind", "website": "", "website_ai_fallback": "Harstad Summits Trail Marathon 2024", "src_url": "https://live.eqtiming.com", "created_date": "2024-03-04 17:06:03", "updated_date": "2024-03-04 17:06:03", "id": "harstad-summits-trail-marathon-2024_20240907_httpsliveeqtimingcom", "extract_id": "e8d9bde1-50da-42d0-bcc4-ac53e890aa8b"}, {"date": "20240907", "type": "terrain", "name": "Finnskogløpet 2024", "distance": "Finnskogløpet 10K, Finnskogløpet 5K, Finnskogløpet Mini (0-5år), Finnskogløpet Mini (6-10år)", "distance_m": [10000, 5000], "place": "Lunderseter, NOR", "organizer": "Lunderseter IL", "website": "", "website_ai_fallback": "Finnskogløpet 2024", "src_url": "https://live.eqtiming.com", "created_date": "2024-03-04 17:06:07", "updated_date": "2024-03-04 17:06:07", "id": "finnskogløpet-2024_20240907_httpsliveeqtimingcom", "extract_id": "5532abe2-356a-45c3-ad55-01de2267ee64"}, {"date": "20240914", "type": "terrain", "name": "Voldsløkka Rundt - Løp 3", "distance": "6 km, 1 km barneløp", "distance_m": [6000, 1000], "place": "Oslo, NOR", "organizer": "Kamp/Vestheim IF", "website": "https://voldslokkarundt.no/", "website_ai_fallback": "Voldsløkka Rundt - Løp 3", "src_url": "https://live.eqtiming.com", "created_date": "2024-03-04 17:06:08", "updated_date": "2024-03-04 17:06:08", "id": "voldsløkka-rundt-løp-3_20240914_httpsliveeqtimingcom", "extract_id": "cca44591-78f7-4c8b-8e12-1ff4c9442bee"}, {"date": "20241012", "type": "terrain", "name": "Furumomila 2024", "distance": "Furumomila 1,5 km, Furumomila 5 km, Furumomila 10 km, Turmarsj 10 km trim", "distance_m": [5000, 10000, 10000], "place": "Furumo Idrettspark, NOR", "organizer": "Modum Friidrettsklubb", "website": "http://www.furumomila.no/", "website_ai_fallback": "Furumomila 2024", "src_url": "https://live.eqtiming.com", "created_date": "2024-03-04 17:06:15", "updated_date": "2024-03-04 17:06:15", "id": "furumomila-2024_20241012_httpsliveeqtimingcom", "extract_id": "b76cb5f4-1c5b-4e91-90a8-44544e9c351f"}, {"date": "20241012", "type": "terrain", "name": "Voldsløkka Rundt - Løp 4", "distance": "6 km, 1 km barneløp", "distance_m": [6000, 1000], "place": "Oslo, NOR", "organizer": "Kamp/Vestheim IF", "website": "https://voldslokkarundt.no/", "website_ai_fallback": "Voldsløkka Rundt - Løp 4", "src_url": "https://live.eqtiming.com", "created_date": "2024-03-04 17:06:17", "updated_date": "2024-03-04 17:06:17", "id": "voldsløkka-rundt-løp-4_20241012_httpsliveeqtimingcom", "extract_id": "bb572330-076c-4a8e-a3b0-5147c01c4440"}, {"date": "20241109", "type": "terrain", "name": "Morothon 2024", "distance": "20 km - Morothon, 10 km - Kortmoro", "distance_m": [20000, 10000], "place": "Søgne, NOR", "organizer": "Søgne IL", "website": "http://www.morothon.no/", "website_ai_fallback": "Morothon 2024", "src_url": "https://live.eqtiming.com", "created_date": "2024-03-04 17:06:24", "updated_date": "2024-03-04 17:06:24", "id": "morothon-2024_20241109_httpsliveeqtimingcom", "extract_id": "267d8aca-0f41-42b5-8f9c-fc94b410bfda"}, {"date": "20240509", "type": "road", "name": "Land Løpskarusell 2 - 2024", "distance": "Land Løpskarusell", "distance_m": [], "place": null, "organizer": null, "website": "", "website_ai_fallback": "Land Løpskarusell 2 - 2024", "src_url": "https://live.eqtiming.com", "created_date": "2024-03-04 17:06:58", "updated_date": "2024-03-04 17:06:58", "id": "land-løpskarusell-2-2024_20240509_httpsliveeqtimingcom", "extract_id": "d2c2f06f-eb7f-44b7-aa4f-6703017d9730"}, {"date": "20240610", "type": "road", "name": "Gauldalsløpet 2024", "distance": "5 km, 10 km, Barneløp", "distance_m": [5000, 10000], "place": "Lundamo, NOR", "organizer": "Lundamo IL", "website": "", "website_ai_fallback": "Gauldalsløpet 2024", "src_url": "https://live.eqtiming.com", "created_date": "2024-03-04 17:06:59", "updated_date": "2024-03-04 17:06:59", "id": "gauldalsløpet-2024_20240610_httpsliveeqtimingcom", "extract_id": "d105753e-dc6a-45d6-9854-552df3181631"}, {"date": "20240703", "type": "road", "name": "Romsdal 5/10/halv", "distance": "5 km, 10 km, Halvmaraton", "distance_m": [5000, 10000, 21097], "place": "Hustadvika, NOR", "organizer": "Molde og Omegn IF", "website": "https://www.romsdal510halv.no/", "website_ai_fallback": "Romsdal 5/10/halv", "src_url": "https://live.eqtiming.com", "created_date": "2024-03-06 21:43:25", "updated_date": "2024-03-06 21:43:25", "id": "romsdal-510halv_20240703_httpsliveeqtimingcom", "extract_id": "f65286d9-a2b9-4cf1-a1db-c62837dbb4c4"}, {"date": "20240406", "type": "terrain", "name": "Mortenløpene 2024 - KM Terrengløp Rogaland", "distance": "Terrengløp barneløype 325m, Terrengløp mini 700m, Terrengløp mini2 1.020 m, Terrengløp kort løype 2,3 km, Terrengløp lang løype 5 km, Lang løype 2 runder 10 km", "distance_m": [5000, 10000], "place": "Njåskogen, NOR", "organizer": "Gjesdal IL", "website": "http://www.gjesdal-il.com/?page_id=321", "website_ai_fallback": "Mortenløpene 2024 - KM Terrengløp Rogaland", "src_url": "https://live.eqtiming.com", "created_date": "2024-03-06 21:53:35", "updated_date": "2024-03-06 21:53:35", "id": "mortenløpene-2024-km-terrengløp-rogaland_20240406_httpsliveeqtimingcom", "extract_id": "d43ac5b2-b0e1-438f-b37c-d576bf522dd3"}, {"date": "20240428", "type": "terrain", "name": "Strailøpet", "distance": "1 km barneløp, 5 km terrengløp, 10 km terrengløp", "distance_m": [1000, 5000, 10000], "place": "Lysløypa på strai, NOR", "organizer": "Kristiansand Løpeklubb", "website": "https://www.facebook.com/profile.php?id=61556489063727", "website_ai_fallback": "Strailøpet", "src_url": "https://live.eqtiming.com", "created_date": "2024-03-10 10:05:49", "updated_date": "2024-03-10 10:05:49", "id": "strailøpet_20240428_httpsliveeqtimingcom", "extract_id": "75588c23-74bc-4ed0-aa0d-a306022e4e24"}, {"date": "20240921", "type": "terrain", "name": "Hvalermila 2024", "distance": "5KM, 10KM", "distance_m": [5000, 10000], "place": "Skjærhalden, Hvaler, NOR", "organizer": "Hvaler IL", "website": "https://www.hvalermila.no/", "website_ai_fallback": "Hvalermila 2024", "src_url": "https://live.eqtiming.com", "created_date": "2024-03-10 10:06:26", "updated_date": "2024-03-10 10:06:26", "id": "hvalermila-2024_20240921_httpsliveeqtimingcom", "extract_id": "ea72437e-225e-4411-9a90-d567358b03b4"}, {"date": "20241020", "type": "terrain", "name": "Gjesdal Trailrun 2024", "distance": "Kort løype uten tidtakning, Lang løype uten tidtakning, Barneløp, 6km, 10km", "distance_m": [6000, 10000], "place": "Ålgård, NOR", "organizer": "Gjesdal IL", "website": "", "website_ai_fallback": "Gjesdal Trailrun 2024", "src_url": "https://live.eqtiming.com", "created_date": "2024-03-10 10:06:31", "updated_date": "2024-03-10 10:06:31", "id": "gjesdal-trailrun-2024_20241020_httpsliveeqtimingcom", "extract_id": "e75075b7-4dd4-484e-bf02-aa34926026d1"}, {"date": "20250111", "type": "road", "name": "HOKA Solastranden Halvmaraton 2025", "distance": "Hoka Solastranden halvmaraton, Hoka Solastranden 10 km, Hoka Solastranden 5 km, Hoka Solastranden Trippelen", "distance_m": [10000, 5000], "place": "Sola Strand Hotel, NOR", "organizer": "Spirit Friidrettsklubb", "website": "http://www.solastrandenhalvmaraton.no/", "website_ai_fallback": "HOKA Solastranden Halvmaraton 2025", "src_url": "https://live.eqtiming.com", "created_date": "2024-03-18 09:14:46", "updated_date": "2024-03-18 09:14:46", "id": "hoka-solastranden-halvmaraton-2025_20250111_httpsliveeqtimingcom", "extract_id": "b4782e76-033e-4ac8-a983-fed25ce0efd2"}]