[{"date": "20240105", "type": "trail", "name": "Night Trail Farsta", "distance": "Night Trail Farsta", "distance_m": [6000, 11000], "place": "Night Trail Farsta", "organizer": "", "website": "https://raceid.com/sv/races/11609/about", "website_ai_fallback": "Night Trail Farsta 6 km, 11 km", "src_url": "https://www.trailrunningsweden.se/trailkalendern/", "created_date": "2023-12-04 16:37:04", "updated_date": "2023-12-04 16:37:04", "id": "night-trail-farsta_20240105_httpswwwtrailrunningswedensetrailkalendern", "extract_id": "d73ff9f9-bbe2-4850-b684-b761f83d98ce"}, {"date": "20240106", "type": "trail", "name": "Borenshill Backyard Ultra", "distance": "Borenshill Backyard Ultra", "distance_m": [53000], "place": "Borenshill Backyard Ultra", "organizer": "", "website": "https://www.bifsportklubb.se/bifsk/nyheter/2018828/nu-kan-du-anmala-dig-till-borenshill-backyard-ultra-2024", "website_ai_fallback": "Borenshill Backyard Ultra 53,648 km", "src_url": "https://www.trailrunningsweden.se/trailkalendern/", "created_date": "2023-12-04 16:37:04", "updated_date": "2023-12-04 16:37:04", "id": "borenshill-backyard-ultra_20240106_httpswwwtrailrunningswedensetrailkalendern", "extract_id": "47d6436a-c9b8-4704-b2c3-61fb2a0bbdca"}, {"date": "20240210", "type": "trail", "name": "Winter Cross Run", "distance": "Winter Cross Run", "distance_m": [4000, 7000, 11000], "place": "Winter Cross Run", "organizer": "", "website": "https://www.wintercrossrun.se", "website_ai_fallback": "Winter Cross Run 4 km, 7,6km, 11,6 km", "src_url": "https://www.trailrunningsweden.se/trailkalendern/", "created_date": "2023-12-04 16:37:04", "updated_date": "2023-12-04 16:37:04", "id": "winter-cross-run_20240210_httpswwwtrailrunningswedensetrailkalendern", "extract_id": "61932cd0-e2b5-4b06-95b1-aabb2da72e78"}, {"date": "20240217", "type": "trail", "name": "Höga kusten Winter Trail", "distance": "Höga kusten Winter Trail", "distance_m": [25000, 35000, 50000], "place": "Höga kusten Winter Trail", "organizer": "", "website": "https://hogakustenwintertrail.se", "website_ai_fallback": "Höga kusten Winter Trail 25 km, 35 km, 50 km", "src_url": "https://www.trailrunningsweden.se/trailkalendern/", "created_date": "2023-12-04 16:37:04", "updated_date": "2023-12-04 16:37:04", "id": "höga-kusten-winter-trail_20240217_httpswwwtrailrunningswedensetrailkalendern", "extract_id": "c12fc4d8-256c-4f79-aeb6-d91e31e0ab32"}, {"date": "20240217", "type": "trail", "name": "Blackyard", "distance": "Blackyard", "distance_m": [3000], "place": "Blackyard", "organizer": "", "website": "https://blackyard.se/", "website_ai_fallback": "Blackyard 3 km", "src_url": "https://www.trailrunningsweden.se/trailkalendern/", "created_date": "2023-12-04 16:37:04", "updated_date": "2023-12-04 16:37:04", "id": "blackyard_20240217_httpswwwtrailrunningswedensetrailkalendern", "extract_id": "2903f1e9-8bc0-4792-bd0a-e797b984a624"}, {"date": "20240309", "type": "trail", "name": "Älvdalen Winter Trail", "distance": "Älvdalen Winter Trail", "distance_m": [], "place": "Älvdalen Winter Trail", "organizer": "", "website": "https://www.alvdalenwintertrail.se/", "website_ai_fallback": "Älvdalen Winter Trail ", "src_url": "https://www.trailrunningsweden.se/trailkalendern/", "created_date": "2023-12-04 16:37:04", "updated_date": "2023-12-04 16:37:04", "id": "älvdalen-winter-trail_20240309_httpswwwtrailrunningswedensetrailkalendern", "extract_id": "b2b9c2ee-191b-4baa-aa08-76d337554ec7"}, {"date": "20240316", "type": "trail", "name": "Ursvik Ultra", "distance": "Ursvik Ultra", "distance_m": [75000], "place": "Ursvik Ultra", "organizer": "", "website": "http://www.ursvikultra.se", "website_ai_fallback": "Ursvik Ultra 75 km, 45 km & 15 km", "src_url": "https://www.trailrunningsweden.se/trailkalendern/", "created_date": "2023-12-04 16:37:04", "updated_date": "2023-12-04 16:37:04", "id": "ursvik-ultra_20240316_httpswwwtrailrunningswedensetrailkalendern", "extract_id": "cf5c8e16-7a4f-4237-9d70-472e7aefdc99"}, {"date": "20240421", "type": "trail", "name": "Isaberg500", "distance": "Isaberg500", "distance_m": [2000, 10000], "place": "Isaberg500", "organizer": "", "website": "https://raceid.com/sv/races/11613/about", "website_ai_fallback": "Isaberg500 2 km, 10,5 km", "src_url": "https://www.trailrunningsweden.se/trailkalendern/", "created_date": "2023-12-04 16:37:04", "updated_date": "2023-12-04 16:37:04", "id": "isaberg500_20240421_httpswwwtrailrunningswedensetrailkalendern", "extract_id": "5b82dbe6-9dfb-429d-97c7-baba6ee9defb"}, {"date": "20240424", "type": "trail", "name": "Kolmården Vertical", "distance": "Kolmården Vertical", "distance_m": [5000], "place": "Kolmården Vertical", "organizer": "", "website": "https://www.kolmardstrailen.se/kolm%C3%A5rden-vertical", "website_ai_fallback": "Kolmården Vertical 5 km", "src_url": "https://www.trailrunningsweden.se/trailkalendern/", "created_date": "2023-12-04 16:37:04", "updated_date": "2023-12-04 16:37:04", "id": "kolmården-vertical_20240424_httpswwwtrailrunningswedensetrailkalendern", "extract_id": "7a70a03c-541a-4691-950b-b89a1f37deaf"}, {"date": "20240512", "type": "trail", "name": "Trailvarvet", "distance": "Trailvarvet", "distance_m": [6000, 11000], "place": "Trailvarvet", "organizer": "", "website": "https://www.goteborgsvarvet.se/varvetveckan/trailvarvet", "website_ai_fallback": "Trailvarvet 6 km, 11,5 km", "src_url": "https://www.trailrunningsweden.se/trailkalendern/", "created_date": "2023-12-04 16:37:04", "updated_date": "2023-12-04 16:37:04", "id": "trailvarvet_20240512_httpswwwtrailrunningswedensetrailkalendern", "extract_id": "1dcb145f-2941-4a80-824d-5cdcade1ed1b"}, {"date": "20240518", "type": "trail", "name": "Borgarloppet", "distance": "Borgarloppet", "distance_m": [0, 2000, 6000, 13000, 23000], "place": "Borgarloppet", "organizer": "", "website": "https://forsaok.se/arrangemang/borgarloppet/", "website_ai_fallback": "Borgarloppet 0,6 km, 2,5 km, 6,0 km, 13 km, 23 km", "src_url": "https://www.trailrunningsweden.se/trailkalendern/", "created_date": "2023-12-04 16:37:04", "updated_date": "2023-12-04 16:37:04", "id": "borgarloppet_20240518_httpswwwtrailrunningswedensetrailkalendern", "extract_id": "be94c4e0-7f25-4212-8b8f-6a8a41a19b40"}, {"date": "20240518", "type": "trail", "name": "Peters Trail", "distance": "Peters Trail", "distance_m": [54000, 107000], "place": "Peters Trail", "organizer": "", "website": "https://www.peterstrail.se/", "website_ai_fallback": "Peters Trail 54 km, 107 km", "src_url": "https://www.trailrunningsweden.se/trailkalendern/", "created_date": "2023-12-04 16:37:04", "updated_date": "2023-12-04 16:37:04", "id": "peters-trail_20240518_httpswwwtrailrunningswedensetrailkalendern", "extract_id": "873368bc-912c-477b-baf2-38c810559378"}, {"date": "20240524", "type": "trail", "name": "Uka Pain", "distance": "Uka Pain", "distance_m": [28000, 50000, 100000, 170000], "place": "Uka Pain", "organizer": "", "website": "https://www.ukapain.se/", "website_ai_fallback": "Uka Pain 28 km, 50 km, 100 km, 170 km", "src_url": "https://www.trailrunningsweden.se/trailkalendern/", "created_date": "2023-12-04 16:37:04", "updated_date": "2023-12-04 16:37:04", "id": "uka-pain_20240524_httpswwwtrailrunningswedensetrailkalendern", "extract_id": "bf0c486f-cbee-413b-8adf-79b02db7b55e"}, {"date": "20240601", "type": "trail", "name": "Skatås ryggar", "distance": "Skatås ryggar", "distance_m": [7000, 14000, 21000], "place": "Skatås ryggar", "organizer": "", "website": "https://www.skatasryggar.se/", "website_ai_fallback": "Skatås ryggar 7 km, 14 km, 21 km", "src_url": "https://www.trailrunningsweden.se/trailkalendern/", "created_date": "2023-12-04 16:37:04", "updated_date": "2023-12-04 16:37:04", "id": "skatås-ryggar_20240601_httpswwwtrailrunningswedensetrailkalendern", "extract_id": "91a9d3d7-d511-4e55-8f83-3392ba3b12f6"}, {"date": "20240606", "type": "trail", "name": "Eketånga Trail", "distance": "Eketånga Trail", "distance_m": [10000], "place": "Eketånga Trail", "organizer": "", "website": "http://eketangatrail.se/", "website_ai_fallback": "Eketånga Trail 10 km", "src_url": "https://www.trailrunningsweden.se/trailkalendern/", "created_date": "2023-12-04 16:37:04", "updated_date": "2023-12-04 16:37:04", "id": "eketånga-trail_20240606_httpswwwtrailrunningswedensetrailkalendern", "extract_id": "b9a49207-3898-4cc9-a28f-618604bb9ce5"}, {"date": "20240615", "type": "trail", "name": "Tjejmilen Sälen by EQPE", "distance": "Tjejmilen Sälen by EQPE", "distance_m": [], "place": "Tjejmilen Sälen by EQPE", "organizer": "", "website": "https://tjejmilen.se/tjejmilen-salen/", "website_ai_fallback": "Tjejmilen Sälen by EQPE 10 km och 5 km", "src_url": "https://www.trailrunningsweden.se/trailkalendern/", "created_date": "2023-12-04 16:37:05", "updated_date": "2023-12-04 16:37:05", "id": "tjejmilen-sälen-by-eqpe_20240615_httpswwwtrailrunningswedensetrailkalendern", "extract_id": "ce429c7a-170b-4bb7-874a-4a0dab88e226"}, {"date": "20240615", "type": "trail", "name": "EcoTrail Stockholm", "distance": "EcoTrail Stockholm", "distance_m": [0, 0, 8000, 16000, 33000, 45000, 80000], "place": "EcoTrail Stockholm", "organizer": "", "website": "https://stockholm.ecotrail.com/sv", "website_ai_fallback": "EcoTrail Stockholm 0,2 km, 0,7 km, 8 km, 16 km, 33 km, 45 km, 80 km", "src_url": "https://www.trailrunningsweden.se/trailkalendern/", "created_date": "2023-12-04 16:37:05", "updated_date": "2023-12-04 16:37:05", "id": "ecotrail-stockholm_20240615_httpswwwtrailrunningswedensetrailkalendern", "extract_id": "827635eb-8b58-4fa9-bf7a-fb7e9878cb70"}, {"date": "20240615", "type": "trail", "name": "Älvdalen Backyard Ultra", "distance": "Älvdalen Backyard Ultra", "distance_m": [6000], "place": "Älvdalen Backyard Ultra", "organizer": "", "website": "https://www.backyardultrasr.se/", "website_ai_fallback": "Älvdalen Backyard Ultra 6,706 km", "src_url": "https://www.trailrunningsweden.se/trailkalendern/", "created_date": "2023-12-04 16:37:05", "updated_date": "2023-12-04 16:37:05", "id": "älvdalen-backyard-ultra_20240615_httpswwwtrailrunningswedensetrailkalendern", "extract_id": "5b73e752-56fe-4486-a747-76bed6713467"}, {"date": "20240630", "type": "trail", "name": "Atea TrailÖvik", "distance": "Atea TrailÖvik", "distance_m": [2000, 6000, 12000, 22000], "place": "Atea TrailÖvik", "organizer": "", "website": "https://trailovik.se/", "website_ai_fallback": "Atea TrailÖvik 2 km, 6 km, 12 km, 22 km", "src_url": "https://www.trailrunningsweden.se/trailkalendern/", "created_date": "2023-12-04 16:37:05", "updated_date": "2023-12-04 16:37:05", "id": "atea-trailövik_20240630_httpswwwtrailrunningswedensetrailkalendern", "extract_id": "5147e4de-5af7-436e-afac-4ac4b3780dc0"}, {"date": "20240707", "type": "trail", "name": "Mora Trail", "distance": "Mora Trail", "distance_m": [2000, 4000, 8000, 17000, 30000], "place": "Mora Trail", "organizer": "", "website": "http://www.moratrail.se/", "website_ai_fallback": "Mora Trail 2 km, 4 km, 8 km, 17 km, 30 km", "src_url": "https://www.trailrunningsweden.se/trailkalendern/", "created_date": "2023-12-04 16:37:05", "updated_date": "2023-12-04 16:37:05", "id": "mora-trail_20240707_httpswwwtrailrunningswedensetrailkalendern", "extract_id": "12e64ec5-8d35-48ce-89be-de73002856a1"}, {"date": "20240713", "type": "trail", "name": "Fäbodlunken", "distance": "Fäbodlunken", "distance_m": [5000, 9000, 17000], "place": "Fäbodlunken", "organizer": "", "website": "https://raceid.com/sv/races/10489/information", "website_ai_fallback": "Fäbodlunken 5 km, 9 km, 17 km", "src_url": "https://www.trailrunningsweden.se/trailkalendern/", "created_date": "2023-12-04 16:37:05", "updated_date": "2023-12-04 16:37:05", "id": "fäbodlunken_20240713_httpswwwtrailrunningswedensetrailkalendern", "extract_id": "4ca8e2f3-de6b-4956-a648-ec0000feaede"}, {"date": "20240727", "type": "trail", "name": "Bjäre trail", "distance": "Bjäre trail", "distance_m": [12000, 17000, 34000, 51000], "place": "Bjäre trail", "organizer": "", "website": "http://www.bjarerun.se", "website_ai_fallback": "Bjäre trail 12 km, 17 km, 34 km, 51 km", "src_url": "https://www.trailrunningsweden.se/trailkalendern/", "created_date": "2023-12-04 16:37:05", "updated_date": "2023-12-04 16:37:05", "id": "bjäre-trail_20240727_httpswwwtrailrunningswedensetrailkalendern", "extract_id": "401e44ed-83b4-4fac-a970-66d47e9d37ed"}, {"date": "20240727", "type": "trail", "name": "Hermanövarvet", "distance": "Hermanövarvet", "distance_m": [15000], "place": "Hermanövarvet", "organizer": "", "website": "http://www.hermanovarvet.se/", "website_ai_fallback": "Hermanövarvet 15 km", "src_url": "https://www.trailrunningsweden.se/trailkalendern/", "created_date": "2023-12-04 16:37:05", "updated_date": "2023-12-04 16:37:05", "id": "hermanövarvet_20240727_httpswwwtrailrunningswedensetrailkalendern", "extract_id": "3c4cedce-a841-4677-9ce8-b4088ebbd875"}, {"date": "20240810", "type": "trail", "name": "Stora Stöten Run", "distance": "Stora Stöten Run", "distance_m": [5000, 13000, 21000], "place": "Stora Stöten Run", "organizer": "", "website": "http://www.storastotenrun.nu", "website_ai_fallback": "Stora Stöten Run 21,6 km, 13,6 km, 5,6 km", "src_url": "https://www.trailrunningsweden.se/trailkalendern/", "created_date": "2023-12-04 16:37:05", "updated_date": "2023-12-04 16:37:05", "id": "stora-stöten-run_20240810_httpswwwtrailrunningswedensetrailkalendern", "extract_id": "0d273f62-add4-427a-bd10-404b81202170"}, {"date": "20240816", "type": "trail", "name": "Trail- och Ultravasan", "distance": "Trail- och Ultravasan", "distance_m": [10000, 30000, 45000, 90000], "place": "Trail- och Ultravasan", "organizer": "", "website": "https://www.vasaloppet.se/lopp/loplopp/ultravasan90/", "website_ai_fallback": "Trail- och Ultravasan 10 km, 30 km, 45 km, 90 km", "src_url": "https://www.trailrunningsweden.se/trailkalendern/", "created_date": "2023-12-04 16:37:05", "updated_date": "2023-12-04 16:37:05", "id": "trail-och-ultravasan_20240816_httpswwwtrailrunningswedensetrailkalendern", "extract_id": "3d227d5e-a630-4747-979d-e0f0b13766fc"}, {"date": "20240831", "type": "trail", "name": "Stockholm Trail", "distance": "Stockholm Trail", "distance_m": [2000, 5000, 10000, 21000], "place": "Stockholm Trail", "organizer": "", "website": "https://stockholmtrail.se/", "website_ai_fallback": "Stockholm Trail 2,5 km, 5 km, 10 km, 21 km", "src_url": "https://www.trailrunningsweden.se/trailkalendern/", "created_date": "2023-12-04 16:37:05", "updated_date": "2023-12-04 16:37:05", "id": "stockholm-trail_20240831_httpswwwtrailrunningswedensetrailkalendern", "extract_id": "5d2c0328-095e-4283-9cc6-f8b8f45ee8cc"}, {"date": "20240906", "type": "trail", "name": "Icebug Xperience West Coast Trail", "distance": "Icebug Xperience West Coast Trail", "distance_m": [30000], "place": "Icebug Xperience West Coast Trail", "organizer": "", "website": "https://icebug.se/west-coast-trail", "website_ai_fallback": "Icebug Xperience West Coast Trail 77 km (21 km, 30 km, 26 km)", "src_url": "https://www.trailrunningsweden.se/trailkalendern/", "created_date": "2023-12-04 16:37:05", "updated_date": "2023-12-04 16:37:05", "id": "icebug-xperience-west-coast-trail_20240906_httpswwwtrailrunningswedensetrailkalendern", "extract_id": "52787912-5ca2-408b-8e91-c11b76321de3"}, {"date": "20240907", "type": "trail", "name": "Göteborg Trailrun", "distance": "Göteborg Trailrun", "distance_m": [9000, 22000], "place": "Göteborg Trailrun", "organizer": "", "website": "https://gbgtrailrun.se/", "website_ai_fallback": "Göteborg Trailrun 9 km, 22 km, 30 km & 44 km", "src_url": "https://www.trailrunningsweden.se/trailkalendern/", "created_date": "2023-12-04 16:37:05", "updated_date": "2023-12-04 16:37:05", "id": "göteborg-trailrun_20240907_httpswwwtrailrunningswedensetrailkalendern", "extract_id": "8de07eb8-1be4-4a38-9c8e-7463e95023a8"}, {"date": "20240907", "type": "trail", "name": "SM / V-SM Trail 35 km", "distance": "SM / V-SM Trail 35 km", "distance_m": [], "place": "SM / V-SM Trail 35 km", "organizer": "", "website": "https://www.halleif.nu/", "website_ai_fallback": "SM / V-SM Trail 35 km ", "src_url": "https://www.trailrunningsweden.se/trailkalendern/", "created_date": "2023-12-04 16:37:05", "updated_date": "2023-12-04 16:37:05", "id": "sm-v-sm-trail-35-km_20240907_httpswwwtrailrunningswedensetrailkalendern", "extract_id": "eb542d70-6726-462d-9f01-29d35d6222c1"}, {"date": "20240908", "type": "trail", "name": "Brevik Trailrun", "distance": "Brevik Trailrun", "distance_m": [3000, 8000], "place": "Brevik Trailrun", "organizer": "", "website": "https://kfumbrevik.se/", "website_ai_fallback": "Brevik Trailrun 3 km, 8 km", "src_url": "https://www.trailrunningsweden.se/trailkalendern/", "created_date": "2023-12-04 16:37:05", "updated_date": "2023-12-04 16:37:05", "id": "brevik-trailrun_20240908_httpswwwtrailrunningswedensetrailkalendern", "extract_id": "4824592c-93fe-492e-b4ab-9e78d2fca036"}, {"date": "20241005", "type": "trail", "name": "Rya Åsar Trail Run", "distance": "Rya Åsar Trail Run", "distance_m": [12000], "place": "Rya Åsar Trail Run", "organizer": "", "website": "https://ryaasartrailrun.se", "website_ai_fallback": "Rya Åsar Trail Run 12 km", "src_url": "https://www.trailrunningsweden.se/trailkalendern/", "created_date": "2023-12-04 16:37:05", "updated_date": "2023-12-04 16:37:05", "id": "rya-åsar-trail-run_20241005_httpswwwtrailrunningswedensetrailkalendern", "extract_id": "6c9fbe5a-b3a4-4de7-9b25-a6db2e01c787"}, {"date": "20241101", "type": "trail", "name": "Kullamannen by UTMB", "distance": "Kullamannen by UTMB", "distance_m": [20000, 50000, 100000, 161000], "place": "Kullamannen by UTMB", "organizer": "", "website": "https://kullamannen.utmb.world/", "website_ai_fallback": "Kullamannen by UTMB 161 km, 100 km, 50 km, 20 km", "src_url": "https://www.trailrunningsweden.se/trailkalendern/", "created_date": "2023-12-04 16:37:05", "updated_date": "2023-12-04 16:37:05", "id": "kullamannen-by-utmb_20241101_httpswwwtrailrunningswedensetrailkalendern", "extract_id": "a512f389-cfc6-427d-b86b-536d1a230433"}, {"date": "20240615", "type": "trail", "name": "BMTR GPX-ULTRA 54k", "distance": "BMTR GPX-ULTRA 54k", "distance_m": [54000], "place": "BMTR GPX-ULTRA 54k", "organizer": "", "website": "https://trailmakaren.webnode.se/bmtr-gpx-ultra-54k/", "website_ai_fallback": "BMTR GPX-ULTRA 54k 54 km", "src_url": "https://www.trailrunningsweden.se/trailkalendern/", "created_date": "2023-12-07 18:17:06", "updated_date": "2023-12-07 18:17:06", "id": "bmtr-gpx-ultra-54k_20240615_httpswwwtrailrunningswedensetrailkalendern", "extract_id": "9295ae97-1e52-4c8e-b13b-73543e2562d9"}, {"date": "20240629", "type": "trail", "name": "Silverleden Ultra 64km", "distance": "64km", "distance_m": [64000], "place": "Silverleden Ultra 64km", "organizer": "", "website": "https://www.silverleden.se/", "website_ai_fallback": "Silverleden Ultra 64km 64km", "src_url": "https://www.trailrunningsweden.se/trailkalendern/", "created_date": "2023-12-16 16:37:31", "updated_date": "2023-12-16 16:37:31", "id": "silverleden-ultra-64km_20240629_httpswwwtrailrunningswedensetrailkalendern", "extract_id": "ad2dbbf4-a417-4459-a7b4-597def4c5034"}, {"date": "20240921", "type": "trail", "name": "Caballo Blanco Memorial Run (CBMR)", "distance": "11 km, 22 km, 44 km", "distance_m": [11000, 22000, 44000], "place": "Caballo Blanco Memorial Run (CBMR)", "organizer": "", "website": "https://redsports.se/CBMR-UCBS", "website_ai_fallback": "Caballo Blanco Memorial Run (CBMR) 11 km, 22 km, 44 km", "src_url": "https://www.trailrunningsweden.se/trailkalendern/", "created_date": "2023-12-16 16:37:31", "updated_date": "2023-12-16 16:37:31", "id": "caballo-blanco-memorial-run-cbmr_20240921_httpswwwtrailrunningswedensetrailkalendern", "extract_id": "115a588c-52a1-4f2c-94d6-76ea200c0759"}, {"date": "20240206", "type": "trail", "name": "Landhof 4-årstider, Vinterloppet 2024", "distance": "5 km, 10 km", "distance_m": [5000, 10000], "place": "Landhof 4-årstider, Vinterloppet 2024", "organizer": "", "website": "https://www.oklandehof.se/skidor/arrangemang/landehof-4-arstider-vinterloppet-2024/", "website_ai_fallback": "Landhof 4-årstider, Vinterloppet 2024 5 km, 10 km", "src_url": "https://www.trailrunningsweden.se/trailkalendern/", "created_date": "2023-12-28 14:28:42", "updated_date": "2023-12-28 14:28:42", "id": "landhof-4-årstider-vinterloppet-2024_20240206_httpswwwtrailrunningswedensetrailkalendern", "extract_id": "60e9a30e-3bde-4e23-9b43-7b135e788866"}, {"date": "20240817", "type": "trail", "name": "Västerås Run", "distance": "14km, 33km", "distance_m": [14000, 33000], "place": "Västerås Run", "organizer": "", "website": "https://www.vasterasrun.se/", "website_ai_fallback": "Västerås Run 14km, 33km", "src_url": "https://www.trailrunningsweden.se/trailkalendern/", "created_date": "2024-01-03 17:00:20", "updated_date": "2024-01-03 17:00:20", "id": "västerås-run_20240817_httpswwwtrailrunningswedensetrailkalendern", "extract_id": "ab4237ef-7526-485a-8a09-48b94d4fd751"}]